scatter3d/__init__.py
scatter3d/index.html
scatter3d/jquery-3.3.1.min.js
scatter3d/scatter3d.py
scatter3d/three.min.js
scatter3d-0.3.1.dist-info/METADATA
scatter3d-0.3.1.dist-info/WHEEL
scatter3d-0.3.1.dist-info/top_level.txt
scatter3d-0.3.1.dist-info/RECORD
