Metadata-Version: 2.1
Name: scatter3d
Version: 0.3.1
Summary: 结合flask生成3d散点模型,并在浏览器中浏览
Home-page: UNKNOWN
Author: wcy
Author-email: 1208640961@qq.com
License: UNKNOWN
Platform: UNKNOWN
